Metadata-Version: 2.1
Name: hoopar
Version: 0.0.0
Summary: Description stub
Author: Jacob Striebel
